{
  "auth": {
    "user_pool_id": "ap-southeast-2_FlJBd60WL",
    "aws_region": "ap-southeast-2",
    "user_pool_client_id": "4n5kqhobl59669rp5kc89g968e",
    "identity_pool_id": "ap-southeast-2:b638c525-07c1-473b-93b4-9c2cfdacfa44",
    "mfa_methods": [],
    "standard_required_attributes": [
      "email"
    ],
    "username_attributes": [
      "email"
    ],
    "user_verification_types": [
      "email"
    ],
    "mfa_configuration": "NONE",
    "password_policy": {
      "min_length": 8,
      "require_numbers": true,
      "require_lowercase": true,
      "require_uppercase": true,
      "require_symbols": true
    },
    "unauthenticated_identities_enabled": true
  },
  "data": {
    "url": "https://ne6o2mwz3nefjbvjbikg2hp2wm.appsync-api.ap-southeast-2.amazonaws.com/graphql",
    "aws_region": "ap-southeast-2",
    "default_authorization_type": "AWS_IAM",
    "authorization_types": [
      "AMAZON_COGNITO_USER_POOLS"
    ],
    "model_introspection": {
      "version": 1,
      "models": {
        "Todo": {
          "name": "Todo",
          "fields": {
            "id": {
              "name": "id",
              "isArray": false,
              "type": "ID",
              "isRequired": true,
              "attributes": []
            },
            "content": {
              "name": "content",
              "isArray": false,
              "type": "String",
              "isRequired": false,
              "attributes": []
            },
            "createdAt": {
              "name": "createdAt",
              "isArray": false,
              "type": "AWSDateTime",
              "isRequired": false,
              "attributes": [],
              "isReadOnly": true
            },
            "updatedAt": {
              "name": "updatedAt",
              "isArray": false,
              "type": "AWSDateTime",
              "isRequired": false,
              "attributes": [],
              "isReadOnly": true
            }
          },
          "syncable": true,
          "pluralName": "Todos",
          "attributes": [
            {
              "type": "model",
              "properties": {}
            },
            {
              "type": "auth",
              "properties": {
                "rules": [
                  {
                    "allow": "public",
                    "provider": "iam",
                    "operations": [
                      "create",
                      "update",
                      "delete",
                      "read"
                    ]
                  }
                ]
              }
            }
          ],
          "primaryKeyInfo": {
            "isCustomPrimaryKey": false,
            "primaryKeyFieldName": "id",
            "sortKeyFieldNames": []
          }
        }
      },
      "enums": {},
      "nonModels": {}
    }
  },
  "version": "1"
}